mlc/config.py
mlc/_version.py
mlc/__init__.py
mlc/cc/compiler.py
mlc/cc/jit.py
mlc/cc/loader.py
mlc/cc/__init__.py
mlc/core/dep_graph.py
mlc/core/device.py
mlc/core/dict.py
mlc/core/dtype.py
mlc/core/error.py
mlc/core/func.py
mlc/core/list.py
mlc/core/object.py
mlc/core/object_path.py
mlc/core/opaque.py
mlc/core/tensor.py
mlc/core/typing.py
mlc/core/__init__.py
mlc/dataclasses/c_class.py
mlc/dataclasses/py_class.py
mlc/dataclasses/utils.py
mlc/dataclasses/__init__.py
mlc/include/dlpack/dlpack.h
mlc/include/mlc/c_api.h
mlc/include/mlc/backtrace/c_api.h
mlc/include/mlc/base/all.h
mlc/include/mlc/base/alloc.h
mlc/include/mlc/base/any.h
mlc/include/mlc/base/base_traits.h
mlc/include/mlc/base/lib.h
mlc/include/mlc/base/optional.h
mlc/include/mlc/base/ref.h
mlc/include/mlc/base/traits_device.h
mlc/include/mlc/base/traits_dtype.h
mlc/include/mlc/base/traits_object.h
mlc/include/mlc/base/traits_scalar.h
mlc/include/mlc/base/traits_str.h
mlc/include/mlc/base/utils.h
mlc/include/mlc/core/all.h
mlc/include/mlc/core/dict.h
mlc/include/mlc/core/dict_base.h
mlc/include/mlc/core/error.h
mlc/include/mlc/core/func.h
mlc/include/mlc/core/func_details.h
mlc/include/mlc/core/list.h
mlc/include/mlc/core/list_base.h
mlc/include/mlc/core/object.h
mlc/include/mlc/core/object_path.h
mlc/include/mlc/core/opaque.h
mlc/include/mlc/core/reflection.h
mlc/include/mlc/core/str.h
mlc/include/mlc/core/tensor.h
mlc/include/mlc/core/typing.h
mlc/include/mlc/core/utils.h
mlc/include/mlc/core/visitor.h
mlc/include/mlc/printer/all.h
mlc/include/mlc/printer/ast.h
mlc/include/mlc/printer/ir_printer.h
mlc/include/mlc/sym/all.h
mlc/include/mlc/sym/analyzer.h
mlc/include/mlc/sym/expr.h
mlc/include/mlc/sym/expr_functor.h
mlc/include/mlc/sym/op.h
mlc/include/mlc/sym/pattern_match.h
mlc/lib/cmake/mlc-shared-0.0.0/mlc-sharedConfig.cmake
mlc/lib/cmake/mlc-shared-0.0.0/mlc-sharedConfigVersion.cmake
mlc/lib/cmake/mlc-shared-0.0.0/mlc-sharedTargets-relwithdebinfo.cmake
mlc_python-0.4.0.dist-info/DELVEWHEEL
mlc_python-0.4.0.dist-info/entry_points.txt
mlc_python-0.4.0.dist-info/METADATA
mlc_python-0.4.0.dist-info/RECORD
mlc_python-0.4.0.dist-info/WHEEL
mlc_python-0.4.0.dist-info/licenses/LICENSE
