Metadata-Version: 2.2
Name: mlc-python
Version: 0.4.0
Summary: Python-first Development for AI Compilers
Author-Email: MLC Authors <junrushao@apache.org>
License:                                  Apache License
Classifier: Programming Language :: Python :: 3
Classifier: Programming Language :: Python :: 3 :: Only
Classifier: License :: OSI Approved :: Apache Software License
Classifier: Intended Audience :: Science/Research
Requires-Python: >=3.9
Requires-Dist: numpy>=1.22
Requires-Dist: ml-dtypes>=0.1
Requires-Dist: Pygments>=2.4.0
Requires-Dist: colorama
Requires-Dist: setuptools; platform_system == "Windows"
Provides-Extra: tests
Requires-Dist: pytest; extra == "tests"
Requires-Dist: torch; extra == "tests"
Requires-Dist: jsonpickle; extra == "tests"
Provides-Extra: dev
Requires-Dist: cython>=3.1; extra == "dev"
Requires-Dist: pre-commit; extra == "dev"
Requires-Dist: pytest; extra == "dev"
Requires-Dist: pipx; extra == "dev"
Requires-Dist: ipdb; extra == "dev"
Requires-Dist: ruff; extra == "dev"
Requires-Dist: mypy; extra == "dev"
Requires-Dist: torch; extra == "dev"
Requires-Dist: jsonpickle; extra == "dev"
